{"fetched": 1779955246.790515, "arrivals": [{"flight": "KL713", "airline": "KLM Asia", "airport": "Amsterdam Schiphol Airport", "iata": "AMS", "time": "28 May 13:34", "status": "Delayed 13:34"}, {"flight": "BW383", "airline": "Caribbean Airlines", "airport": "Georgetown Eugene F. Correira International Airport", "iata": "OGL", "time": "28 May 14:15", "status": "Scheduled"}, {"flight": "PY422", "airline": "Surinam Airways", "airport": "Georgetown Cheddi Jagan International Airport", "iata": "GEO", "time": "28 May 20:15", "status": "Scheduled"}, {"flight": "M6844", "airline": "Amerijet International", "airport": "Port of Spain Piarco International Airport", "iata": "POS", "time": "29 May 07:25", "status": "Scheduled"}, {"flight": "KL713", "airline": "KLM", "airport": "Amsterdam Schiphol Airport", "iata": "AMS", "time": "29 May 13:15", "status": "Scheduled"}, {"flight": "PY431", "airline": "Surinam Airways", "airport": "Willemstad Curacao Hato International Airport", "iata": "CUR", "time": "29 May 14:20", "status": "Scheduled"}, {"flight": "PY993", "airline": "Surinam Airways", "airport": "Amsterdam Schiphol Airport", "iata": "AMS", "time": "29 May 14:50", "status": "Scheduled"}, {"flight": "CM318", "airline": "Copa Airlines", "airport": "Panama City Tocumen International Airport", "iata": "PTY", "time": "29 May 16:37", "status": "Scheduled"}], "departures": [{"flight": "PY421", "airline": "Surinam Airways", "airport": "Georgetown Cheddi Jagan International Airport", "iata": "GEO", "time": "28 May 06:00", "status": "Scheduled"}, {"flight": "BW384", "airline": "Caribbean Airlines", "airport": "Georgetown Eugene F. Correira International Airport", "iata": "OGL", "time": "28 May 15:15", "status": "Scheduled"}, {"flight": "KL714", "airline": "KLM", "airport": "Amsterdam Schiphol Airport", "iata": "AMS", "time": "28 May 16:15", "status": "Canceled"}, {"flight": "PY431", "airline": "Surinam Airways", "airport": "Oranjestad Queen Beatrix International Airport", "iata": "AUA", "time": "29 May 06:30", "status": "Scheduled"}, {"flight": "M6844", "airline": "Amerijet International", "airport": "Miami International Airport", "iata": "MIA", "time": "29 May 09:25", "status": "Scheduled"}, {"flight": "8W725", "airline": "Fly AllWays", "airport": "Georgetown Cheddi Jagan International Airport", "iata": "GEO", "time": "29 May 11:00", "status": "Scheduled"}, {"flight": "KL714", "airline": "KLM", "airport": "Amsterdam Schiphol Airport", "iata": "AMS", "time": "29 May 16:15", "status": "Canceled"}], "updated": "28 May 2026 05:00 SR", "api_success": true}