{"fetched": 1778375739.389061, "arrivals": [{"flight": "W12493", "airline": "Unknown", "airport": "Georgetown Eugene F. Correira International Airport", "iata": "OGL", "time": "10 May 09:45", "status": "Scheduled"}, {"flight": "GUM42", "airline": "Gum Air", "airport": "Georgetown Eugene F. Correira International Airport", "iata": "OGL", "time": "11 May 10:15", "status": "Scheduled"}, {"flight": "W12492", "airline": "Unknown", "airport": "Georgetown Eugene F. Correira International Airport", "iata": "OGL", "time": "11 May 10:15", "status": "Scheduled"}], "departures": [{"flight": "W12494", "airline": "Unknown", "airport": "Georgetown Eugene F. Correira International Airport", "iata": "OGL", "time": "10 May 10:30", "status": "Scheduled"}, {"flight": "GUM41", "airline": "Gum Air", "airport": "Georgetown Eugene F. Correira International Airport", "iata": "OGL", "time": "11 May 07:30", "status": "Scheduled"}, {"flight": "W12491", "airline": "Unknown", "airport": "Georgetown Eugene F. Correira International Airport", "iata": "OGL", "time": "11 May 07:30", "status": "Scheduled"}], "updated": "09 May 2026 22:15 SR", "api_success": true}