{"fetched": 1780032888.901444, "extremes": [{"dt": 1780019252, "date": "2026-05-29T01:47+0000", "height": -0.773, "type": "Low"}, {"dt": 1780039199, "date": "2026-05-29T07:19+0000", "height": 1.066, "type": "High"}, {"dt": 1780064436, "date": "2026-05-29T14:20+0000", "height": -1.038, "type": "Low"}, {"dt": 1780084190, "date": "2026-05-29T19:49+0000", "height": 0.824, "type": "High"}, {"dt": 1780108066, "date": "2026-05-30T02:27+0000", "height": -0.78, "type": "Low"}, {"dt": 1780127759, "date": "2026-05-30T07:55+0000", "height": 1.109, "type": "High"}, {"dt": 1780153214, "date": "2026-05-30T15:00+0000", "height": -1.08, "type": "Low"}, {"dt": 1780172816, "date": "2026-05-30T20:26+0000", "height": 0.834, "type": "High"}, {"dt": 1780196769, "date": "2026-05-31T03:06+0000", "height": -0.783, "type": "Low"}, {"dt": 1780216245, "date": "2026-05-31T08:30+0000", "height": 1.126, "type": "High"}, {"dt": 1780241888, "date": "2026-05-31T15:38+0000", "height": -1.103, "type": "Low"}, {"dt": 1780261381, "date": "2026-05-31T21:03+0000", "height": 0.824, "type": "High"}], "updated": "29 May 2026 02:34 SR"}